AUTHORS.rst
CONTRIBUTING.rst
HISTORY.rst
LICENSE
MANIFEST.in
README.rst
setup.cfg
setup.py
docs/Makefile
docs/authors.rst
docs/conf.py
docs/contributing.rst
docs/history.rst
docs/index.rst
docs/installation.rst
docs/make.bat
docs/modules.rst
docs/pyzlog.rst
docs/readme.rst
docs/usage.rst
pyzlog/__init__.py
pyzlog.egg-info/PKG-INFO
pyzlog.egg-info/SOURCES.txt
pyzlog.egg-info/dependency_links.txt
pyzlog.egg-info/not-zip-safe
pyzlog.egg-info/top_level.txt
tests/__init__.py
tests/test_pyzlog.py