Metadata-Version: 1.0
Name: pyzlog
Version: 0.1.3
Summary: Simple python module to standardize logging for applications
Home-page: https://github.com/zeeto/pyzlog
Author: UNKNOWN
Author-email: UNKNOWN
License: ISCL
Keywords: pyzlog
Platform: UNKNOWN
Classifier: Development Status :: 2 - Pre-Alpha
Classifier: Intended Audience :: Developers
Classifier: License :: OSI Approved :: ISC License (ISCL)
Classifier: Natural Language :: English
Classifier: Programming Language :: Python :: 2
Classifier: Programming Language :: Python :: 2.6
Classifier: Programming Language :: Python :: 2.7
